flask_tortoise/__init__.py
flask_tortoise/cli.py
flask_tortoise/fields.py
flask_tortoise/models.py
flask_tortoise/queryset.py
Flask_Tortoise-0.0.2.dist-info/LICENSE
Flask_Tortoise-0.0.2.dist-info/METADATA
Flask_Tortoise-0.0.2.dist-info/WHEEL
Flask_Tortoise-0.0.2.dist-info/top_level.txt
Flask_Tortoise-0.0.2.dist-info/RECORD
