Metadata-Version: 2.1
Name: Flask-Tortoise
Version: 0.0.2
Summary: Adds asynchronous Tortoise ORM support for flask app.
Home-page: https://github.com/marktennyson/Flask-Tortoise
Author: Aniket Sarkar
Author-email: aniketsarkar@yahoo.com
License: GNU General Public License v3 or later (GPLv3+)
Keywords: flask,flask-tortoise,Tortoise
Platform: any
Classifier: Development Status :: 5 - Production/Stable
Classifier: Environment :: Web Environment
Classifier: Framework :: Flask
Classifier: Intended Audience :: Developers
Classifier: License :: OSI Approved :: GNU General Public License v3 or later (GPLv3+)
Classifier: Operating System :: OS Independent
Classifier: Programming Language :: Python
Classifier: Programming Language :: Python :: 3
Classifier: Programming Language :: Python :: 3 :: Only
Classifier: Programming Language :: Python :: 3.6
Classifier: Programming Language :: Python :: 3.7
Classifier: Programming Language :: Python :: 3.8
Classifier: Programming Language :: Python :: 3.9
Classifier: Programming Language :: Python :: Implementation :: CPython
Classifier: Programming Language :: Python :: Implementation :: PyPy
Classifier: Topic :: Software Development :: Libraries :: Python Modules
Requires-Python: >=3.6,<4
License-File: LICENSE
Requires-Dist: tortoise-orm (>=0.17.7)
Requires-Dist: asgiref (>=3.4.1)
Requires-Dist: aerich (>=0.5.8)
Requires-Dist: nc-console (>=0.0.4)
